trash101/__init__.py
trash101/putback.py
trash101/trash.py
trash101-0.2.0.dist-info/entry_points.txt
trash101-0.2.0.dist-info/LICENSE
trash101-0.2.0.dist-info/WHEEL
trash101-0.2.0.dist-info/METADATA
trash101-0.2.0.dist-info/RECORD
